runmcp_in_e2b/.env
runmcp_in_e2b/__init__.py
runmcp_in_e2b/__main__.py
runmcp_in_e2b/bomcfault.py
runmcp_in_e2b/fast_mcp_sandbox.py
runmcp_in_e2b/mcp_box.py
runmcp_in_e2b/runmcp.py
runmcp_in_e2b-0.5.8.dist-info/METADATA
runmcp_in_e2b-0.5.8.dist-info/WHEEL
runmcp_in_e2b-0.5.8.dist-info/entry_points.txt
runmcp_in_e2b-0.5.8.dist-info/licenses/LICENSE.txt
runmcp_in_e2b-0.5.8.dist-info/RECORD
