Metadata-Version: 2.4
Name: runmcp-in-e2b
Version: 0.5.8
Summary: Bomc MCP Server
Author: Goosezzy
Maintainer-email: zhangx <goosezzy612@gmail.com>
License: MIT
License-File: LICENSE.txt
Keywords: automation,e2b,mcp,tool
Classifier: Development Status :: 4 - Beta
Classifier: Intended Audience :: Developers
Classifier: License :: OSI Approved :: MIT License
Classifier: Programming Language :: Python :: 3
Classifier: Programming Language :: Python :: 3.13
Requires-Python: >=3.10
Requires-Dist: click>=8.2.1
Requires-Dist: e2b-code-interpreter>=1.5.2
Requires-Dist: mcp>=1.12.1
Requires-Dist: starlette==0.45.3
Requires-Dist: uvicorn>=0.34.3
